whiffpy/__init__.py
whiffpy/cli.py
whiffpy/error_analyzer.py
whiffpy/explainer.py
whiffpy/runner.py
whiffpy/utils.py
whiffpy-0.1.3.dist-info/entry_points.txt
whiffpy-0.1.3.dist-info/licenses/LICENSE
whiffpy-0.1.3.dist-info/METADATA
whiffpy-0.1.3.dist-info/WHEEL
whiffpy-0.1.3.dist-info/RECORD
