Metadata-Version: 2.4
Name: whiffpy
Version: 0.1.3
Summary: Smart code explainer for Python
License: MIT
License-File: LICENSE
Author: Parmeet Singh Bhamrah
Author-email: parmeetbhamrah@gmail.com
Requires-Python: >=3.9
Classifier: License :: OSI Approved :: MIT License
Classifier: Programming Language :: Python :: 3
Classifier: Programming Language :: Python :: 3.9
Classifier: Programming Language :: Python :: 3.10
Classifier: Programming Language :: Python :: 3.11
Classifier: Programming Language :: Python :: 3.12
Classifier: Programming Language :: Python :: 3.13
Classifier: Programming Language :: Python :: 3.14
